<?xml version="1.0" encoding="us-ascii"?>
<XML ID="EQInterfaceDefinitionLanguage">
  <Schema xmlns="EverQuestData" xmlns:dt="EverQuestDataTypes" />
  <Gauge item="Casting_Gauge">
    <ScreenID>Gauge</ScreenID>
    <Font>3</Font>
    <TextColor>
      <R>240</R>
      <G>240</G>
      <B>0</B>
    </TextColor>
    <RelativePosition>true</RelativePosition>
    <Location>
      <X>4</X>
      <Y>25</Y>
    </Location>
    <Size>
      <CX>361</CX>
      <CY>16</CY>
    </Size>
    <GaugeOffsetY>0</GaugeOffsetY>
    <TextOffsetX>-550</TextOffsetX>
    <Style_VScroll>false</Style_VScroll>
    <Style_HScroll>false</Style_HScroll>
    <Style_Transparent>false</Style_Transparent>
    <TooltipReference />
    <FillTint>
      <R>255</R>
      <G>0</G>
      <B>255</B>
      <Alpha>255</Alpha>
    </FillTint>
    <LinesFillTint>
      <R>240</R>
      <G>240</G>
      <B>0</B>
    </LinesFillTint>
    <DrawLinesFill>false</DrawLinesFill>
    <EQType>7</EQType>
    <GaugeDrawTemplate>
      <Fill>EVO_Target_GaugeFill</Fill>
      <Background>EVO_Target_GaugeFill</Background>
    </GaugeDrawTemplate>
  </Gauge>
  <Label item="Casting_SpellName">
    <ScreenID>Casting_SpellName</ScreenID>
    <EQType>134</EQType>
    <!--<Font>3</Font>-->
    <Text>Long Spell Name</Text>
    <RelativePosition>true</RelativePosition>
    <Location>
      <X>-21</X>
      <Y>4</Y>
    </Location>
    <Size>
      <CX>412</CX>
      <CY>18</CY>
    </Size>
    <Text>0</Text>
    <TextColor>
      <R>255</R>
      <G>255</G>
      <B>255</B>
      <Alpha>255</Alpha>
    </TextColor>
    <NoWrap>true</NoWrap>
    <AlignCenter>true</AlignCenter>
    <AlignRight>false</AlignRight>
    <AlignLeft>false</AlignLeft>
    <Font>5</Font>
  </Label>
  <Label item="Casting_SpellName1">
    <ScreenID>Casting_SpellName1</ScreenID>
    <EQType>134</EQType>
    <!--<Font>3</Font>-->
    <Text>Long Spell Name</Text>
    <RelativePosition>true</RelativePosition>
    <Location>
      <X>-22</X>
      <Y>3</Y>
    </Location>
    <Size>
      <CX>412</CX>
      <CY>18</CY>
    </Size>
    <Text>0</Text>
    <TextColor>
      <R>0</R>
      <G>0</G>
      <B>0</B>
      <Alpha>255</Alpha>
    </TextColor>
    <NoWrap>true</NoWrap>
    <AlignCenter>true</AlignCenter>
    <AlignRight>false</AlignRight>
    <AlignLeft>false</AlignLeft>
    <Font>5</Font>
  </Label>
  <Label item="Casting_SpellName2">
    <ScreenID>Casting_SpellName2</ScreenID>
    <EQType>134</EQType>
    <!--<Font>3</Font>-->
    <Text>Long Spell Name</Text>
    <RelativePosition>true</RelativePosition>
    <Location>
      <X>-20</X>
      <Y>3</Y>
    </Location>
    <Size>
      <CX>412</CX>
      <CY>18</CY>
    </Size>
    <Text>0</Text>
    <TextColor>
      <R>0</R>
      <G>0</G>
      <B>0</B>
      <Alpha>255</Alpha>
    </TextColor>
    <NoWrap>true</NoWrap>
    <AlignCenter>true</AlignCenter>
    <AlignRight>false</AlignRight>
    <AlignLeft>false</AlignLeft>
    <Font>5</Font>
  </Label>
  <Label item="Casting_SpellName3">
    <ScreenID>Casting_SpellName3</ScreenID>
    <EQType>134</EQType>
    <!--<Font>3</Font>-->
    <Text>Long Spell Name</Text>
    <RelativePosition>true</RelativePosition>
    <Location>
      <X>-22</X>
      <Y>5</Y>
    </Location>
    <Size>
      <CX>412</CX>
      <CY>18</CY>
    </Size>
    <Text>0</Text>
    <TextColor>
      <R>0</R>
      <G>0</G>
      <B>0</B>
      <Alpha>255</Alpha>
    </TextColor>
    <NoWrap>true</NoWrap>
    <AlignCenter>true</AlignCenter>
    <AlignRight>false</AlignRight>
    <AlignLeft>false</AlignLeft>
    <Font>5</Font>
  </Label>
  <Label item="Casting_SpellName4">
    <ScreenID>Casting_SpellName4</ScreenID>
    <EQType>134</EQType>
    <!--<Font>3</Font>-->
    <Text>Long Spell Name</Text>
    <RelativePosition>true</RelativePosition>
    <Location>
      <X>-20</X>
      <Y>5</Y>
    </Location>
    <Size>
      <CX>412</CX>
      <CY>18</CY>
    </Size>
    <Text>0</Text>
    <TextColor>
      <R>0</R>
      <G>0</G>
      <B>0</B>
      <Alpha>255</Alpha>
    </TextColor>
    <NoWrap>true</NoWrap>
    <AlignCenter>true</AlignCenter>
    <AlignRight>false</AlignRight>
    <AlignLeft>false</AlignLeft>
    <Font>5</Font>
  </Label>
  <Screen item="CastingWindow">
    <!--<ScreenID/>-->
    <!--<Font/>-->
    <RelativePosition>false</RelativePosition>
    <Location>
      <X>290</X>
      <Y>60</Y>
    </Location>
    <Size>
      <CX>370</CX>
      <CY>45</CY>
    </Size>
    <Text>Casting Time</Text>
    <Style_VScroll>false</Style_VScroll>
    <Style_HScroll>false</Style_HScroll>
    <Style_Transparent>true</Style_Transparent>
    <TooltipReference>The Breath Meter</TooltipReference>
    <DrawTemplate>WDT_RoundedNoTitle</DrawTemplate>
    <Style_Titlebar>false</Style_Titlebar>
    <Style_Closebox>false</Style_Closebox>
    <Style_Minimizebox>false</Style_Minimizebox>
    <Style_Border>false</Style_Border>
    <Style_Sizable>false</Style_Sizable>
    <Pieces>Casting_Gauge</Pieces>
    <Pieces>Casting_SpellName1</Pieces>
    <Pieces>Casting_SpellName2</Pieces>
    <Pieces>Casting_SpellName3</Pieces>
    <Pieces>Casting_SpellName4</Pieces>
    <Pieces>Casting_SpellName</Pieces>
    <Font>5</Font>
  </Screen>
</XML>